<annotation>
	<folder>train</folder>
	<filename>rw3.jpg</filename>
	<path>D:\object_detection_google_colab\training_demo\images\train\rw3.jpg</path>
	<source>
		<database>Unknown</database>
	</source>
	<size>
		<width>600</width>
		<height>638</height>
		<depth>3</depth>
	</size>
	<segmented>0</segmented>
	<object>
		<name>ringworm</name>
		<pose>Unspecified</pose>
		<truncated>0</truncated>
		<difficult>0</difficult>
		<bndbox>
			<xmin>267</xmin>
			<ymin>318</ymin>
			<xmax>321</xmax>
			<ymax>372</ymax>
		</bndbox>
	</object>
	<object>
		<name>ringworm</name>
		<pose>Unspecified</pose>
		<truncated>0</truncated>
		<difficult>0</difficult>
		<bndbox>
			<xmin>199</xmin>
			<ymin>347</ymin>
			<xmax>223</xmax>
			<ymax>380</ymax>
		</bndbox>
	</object>
	<object>
		<name>ringworm</name>
		<pose>Unspecified</pose>
		<truncated>0</truncated>
		<difficult>0</difficult>
		<bndbox>
			<xmin>154</xmin>
			<ymin>362</ymin>
			<xmax>208</xmax>
			<ymax>413</ymax>
		</bndbox>
	</object>
	<object>
		<name>ringworm</name>
		<pose>Unspecified</pose>
		<truncated>0</truncated>
		<difficult>0</difficult>
		<bndbox>
			<xmin>396</xmin>
			<ymin>345</ymin>
			<xmax>462</xmax>
			<ymax>423</ymax>
		</bndbox>
	</object>
</annotation>
