<annotation>
	<folder>train</folder>
	<filename>train15.jpg</filename>
	<path>D:\object_detection_google_colab\training_demo\images\train\train15.jpg</path>
	<source>
		<database>Unknown</database>
	</source>
	<size>
		<width>772</width>
		<height>1024</height>
		<depth>3</depth>
	</size>
	<segmented>0</segmented>
	<object>
		<name>ringworm</name>
		<pose>Unspecified</pose>
		<truncated>0</truncated>
		<difficult>0</difficult>
		<bndbox>
			<xmin>459</xmin>
			<ymin>399</ymin>
			<xmax>568</xmax>
			<ymax>471</ymax>
		</bndbox>
	</object>
</annotation>
